comaps_map_distributor/__init__.py
comaps_map_distributor/app.py
comaps_map_distributor/downloader.py
comaps_map_distributor/server.py
comaps_map_distributor-0.2.0.dist-info/licenses/COPYING
comaps_map_distributor-0.2.0.dist-info/WHEEL
comaps_map_distributor-0.2.0.dist-info/entry_points.txt
comaps_map_distributor-0.2.0.dist-info/METADATA
comaps_map_distributor-0.2.0.dist-info/RECORD
