Metadata-Version: 2.4
Name: comaps-map-distributor
Version: 0.2.0
Summary: A small CLI tool to download and then serve map files for CoMaps.
Keywords: comaps,openstreetmap,map server
Author: Bastian Greshake Tzovaras
Author-email: Bastian Greshake Tzovaras <bgreshake@proton.me>
License-Expression: AGPL-3.0-or-later
License-File: COPYING
Requires-Dist: click>=8.3.1
Requires-Dist: inquirerpy>=0.3.4
Requires-Dist: netifaces>=0.11.0
Requires-Dist: rangehttpserver>=1.4.0
Requires-Dist: requests>=2.32.5
Requires-Dist: rich>=14.2.0
Requires-Python: >=3.12
Project-URL: Changelog, https://codeberg.org/gedankenstuecke/comaps-map-distributor/src/branch/main/CHANGELOG.md
Project-URL: Funding, https://ko-fi.com/gedankenstuecke
Project-URL: Homepage, https://codeberg.org/gedankenstuecke/comaps-map-distributor
Project-URL: Issues, https://codeberg.org/gedankenstuecke/comaps-map-distributor/issues
Project-URL: Repository, https://codeberg.org/gedankenstuecke/comaps-map-distributor.git
